scpopcorn/__init__.py
scpopcorn/scpopcorn.py
scpopcorn-0.1.20.dist-info/LICENSE
scpopcorn-0.1.20.dist-info/METADATA
scpopcorn-0.1.20.dist-info/WHEEL
scpopcorn-0.1.20.dist-info/top_level.txt
scpopcorn-0.1.20.dist-info/RECORD
