Metadata-Version: 2.1
Name: scpopcorn
Version: 0.1.20
Summary: PopCorn is a new method for the identification of sub-populations of cells present within individual single cell experiments and mapping of these sub-populations across the experiments.
Home-page: https://github.com/ncbi/scPopCorn
Author: Yijie Wang
Author-email: yijwang@iu.edu
License: GNU General Public License v3
Platform: UNKNOWN
Requires-Dist: numpy (>=1.14.2)
Requires-Dist: pandas (>=0.22.0)
Requires-Dist: anndata (>=0.6.10)
Requires-Dist: scipy (>=1.0.0)
Requires-Dist: matplotlib (>=3.0.0)
Requires-Dist: scanpy (>=1.3.1)
Requires-Dist: scikit-learn (>=0.20.0)
Requires-Dist: hub-toolbox (>=2.3.1)
Requires-Dist: cvxpy (>=1.0.6)
